sentinel1decoder-1.1.1.dist-info/METADATA
sentinel1decoder-1.1.1.dist-info/WHEEL
sentinel1decoder-1.1.1.dist-info/licenses/LICENSE
sentinel1decoder/__init__.py
sentinel1decoder/_headers.py
sentinel1decoder/_sentinel1decoder.cpython-314-powerpc64le-linux-gnu.so
sentinel1decoder/_sentinel1decoder.pyi
sentinel1decoder/constants.py
sentinel1decoder/l0decoder.py
sentinel1decoder/l0file.py
sentinel1decoder/py.typed
sentinel1decoder/utilities.py
sentinel1decoder-1.1.1.dist-info/RECORD
