Metadata-Version: 2.4
Name: sentinel1decoder
Version: 1.1.1
Classifier: Programming Language :: Rust
Classifier: Programming Language :: Python :: Implementation :: CPython
Classifier: Programming Language :: Python :: Implementation :: PyPy
Classifier: License :: OSI Approved :: GNU General Public License v3 (GPLv3)
Classifier: Operating System :: OS Independent
Requires-Dist: numpy>=1.24
Requires-Dist: pandas
Requires-Dist: maturin>=1.4.0 ; extra == 'dev'
Requires-Dist: pytest ; extra == 'dev'
Requires-Dist: pytest-cov ; extra == 'dev'
Requires-Dist: pre-commit ; extra == 'dev'
Requires-Dist: black==24.2 ; extra == 'dev'
Requires-Dist: flake8==7.0 ; extra == 'dev'
Requires-Dist: autoflake ; extra == 'dev'
Requires-Dist: isort==5.13.2 ; extra == 'dev'
Requires-Dist: mypy==1.8.0 ; extra == 'dev'
Requires-Dist: jupyter ; extra == 'dev'
Requires-Dist: jupyterlab ; extra == 'dev'
Requires-Dist: ipywidgets ; extra == 'dev'
Requires-Dist: scipy ; extra == 'dev'
Requires-Dist: matplotlib ; extra == 'dev'
Requires-Dist: pandas-stubs ; extra == 'dev'
Provides-Extra: dev
License-File: LICENSE
Summary: A python decoder for ESA Sentinel-1 Level0 files
License: GPL-3.0
Requires-Python: >=3.8
Project-URL: Homepage, https://github.com/Rich-Hall/sentinel1decoder
